exifScan/CreateMetadata.py
exifScan/ExifToolScan.py
exifScan/__init__.py
exifScan/__main__.py
exifScan/dualLogging.py
exifScan/geoDfFromExifDf.py
exifScan/runExifScan.py
exifScan/watchDirectory.py
exifScan/writeKart.py
exifScan/creditosfolium/__init__.py
exifScan/creditosfolium/creditosfolium.py
exifScan/generateHTML/__init__.py
exifScan/generateHTML/createHTML.py
exifScan/generateHTML/generateHTMLSnippets.py
exifScan/generateHTML/info.jpg
exifScan/generateHTML/nouislider.min.css
exifScan/generateHTML/nouislider.min.js
exifScan/generateHTML/styles.css
exifScan/metashape/PsxLocator.py
exifScan/metashape/__init__.py
persistentObserver/__init__.py
persistentObserver/folderUpdateHandler.py
persistentObserver/persistentObserver.py
image_location_scan-0.2.22.dist-info/METADATA
image_location_scan-0.2.22.dist-info/WHEEL
image_location_scan-0.2.22.dist-info/top_level.txt
image_location_scan-0.2.22.dist-info/RECORD
