Metadata-Version: 2.1
Name: image_location_scan
Version: 0.2.22
Summary: A tool that uses exifdata to organise geolocated image files (e.g. drones images) into a geopackage file with associated metadata. Additional features, such as can also create a webpage with a leaflet map.
Author-email: Jonathan Davidson <jrjdavidson@gmail.com>
Keywords: exiftool,drone,geolocation,photography,photogrammetry,Metashape,leaflet,folium
Classifier: Development Status :: 3 - Alpha
Classifier: Programming Language :: Python :: 3
Classifier: License :: OSI Approved :: MIT License
Classifier: Operating System :: OS Independent
Requires-Python: >=3.8
Requires-Dist: beautifulsoup4==4.12.3
Requires-Dist: branca==0.7.2
Requires-Dist: folium==0.17.0
Requires-Dist: geopandas==1.0.0
Requires-Dist: Jinja2==3.1.3
Requires-Dist: numpy==2.0.1
Requires-Dist: pandas==2.2.2
Requires-Dist: pyogrio==0.9.0
Requires-Dist: watchdog==4.0.0
Requires-Dist: openpyxl==3.1.5
